Metadata-Version: 1.0
Name: django-raven-heka
Version: 0.3
Summary: Django+Raven+heka integration
Home-page: https://github.com/mozilla-services/django-raven-heka
Author: Victor Ng
Author-email: vng@mozilla.com
License: MPLv2.0
Keywords: django heka raven sentry
Platform: UNKNOWN
Classifier: License :: OSI Approved :: Mozilla Public License 2.0 (MPL 2.0)
Classifier: Intended Audience :: Developers
Classifier: Intended Audience :: System Administrators
Classifier: Operating System :: OS Independent
Classifier: Topic :: Software Development
